pyzeptrion/__init__.py
pyzeptrion/blind.py
pyzeptrion/bulb.py
pyzeptrion/cli.py
pyzeptrion/const.py
pyzeptrion/device.py
pyzeptrion/discover.py
pyzeptrion/exceptions.py
pyzeptrion-1.0.0.dist-info/LICENSE
pyzeptrion-1.0.0.dist-info/METADATA
pyzeptrion-1.0.0.dist-info/WHEEL
pyzeptrion-1.0.0.dist-info/top_level.txt
pyzeptrion-1.0.0.dist-info/RECORD
