Metadata-Version: 2.1
Name: pyzeptrion
Version: 1.0.0
Summary: Classes to interact with Zeptrion devices made by Feller
Author-email: Thierry Perroud <astronaut@footprintsonthemoon.ch>
License: MIT
Project-URL: homepage, https://github.com/footprintsonthemoon/zeptrion_python
Project-URL: documentation, https://github.com/footprintsonthemoon/zeptrion_python
Project-URL: repository, https://github.com/footprintsonthemoon/zeptrion_python
Keywords: zeptrion,home assistant,library
Classifier: Programming Language :: Python :: 3.10
Classifier: License :: OSI Approved :: MIT License
Classifier: Operating System :: OS Independent
Classifier: Development Status :: 1 - Planning
Classifier: Intended Audience :: Developers
Classifier: Topic :: Home Automation
Requires-Python: >=3.10
License-File: LICENSE
Requires-Dist: asyncio
Requires-Dist: aiohttp
Requires-Dist: zeroconf
